{
  "threshold_level": 0,
  "phase": "2단계",
  "regime": "스태그플레이션",
  "momentum_top3": [
    "TQQQ",
    "UPRO",
    "SPXL"
  ],
  "momentum_scores": {
    "TQQQ": 6,
    "UPRO": 5,
    "SPXL": 5,
    "SOXL": 5,
    "122630.KS": 5,
    "LABU": 4,
    "FNGU": 4,
    "BIL": 4,
    "SCHP": 4,
    "XLE": 3,
    "XLP": 3,
    "233740.KS": 3,
    "SQQQ": 1,
    "SPXU": 1,
    "SOXS": 1,
    "TLT": 1,
    "XLV": 1,
    "FAS": 0,
    "GLD": 0
  },
  "falling_knife_active": false,
  "fx_level": "high",
  "ism_level": "unknown",
  "fed_bs_trend": "expanding",
  "pc_level": "unknown",
  "fg_zone": "unknown",
  "last_vix": 17.079999923706055,
  "last_updated": "2026-05-08T02:50:19.156315+00:00"
}