{
  "threshold_level": 0,
  "phase": "2단계",
  "regime": "스태그플레이션",
  "momentum_top3": [
    "122630.KS",
    "TQQQ",
    "UPRO"
  ],
  "momentum_scores": {
    "122630.KS": 6,
    "TQQQ": 5,
    "UPRO": 5,
    "SPXL": 5,
    "SOXL": 5,
    "LABU": 5,
    "FNGU": 4,
    "BIL": 4,
    "SCHP": 4,
    "XLP": 3,
    "XLE": 2,
    "233740.KS": 2,
    "SQQQ": 1,
    "SOXS": 1,
    "GLD": 1,
    "XLV": 1,
    "FAS": 0,
    "SPXU": 0,
    "TLT": 0
  },
  "falling_knife_active": false,
  "fx_level": "high",
  "ism_level": "unknown",
  "fed_bs_trend": "expanding",
  "pc_level": "unknown",
  "fg_zone": "unknown",
  "last_vix": 18.049999237060547,
  "last_updated": "2026-05-13T16:19:25.907771+00:00"
}